coveo_systools/__init__.py
coveo_systools/filesystem.py
coveo_systools/platforms.py
coveo_systools/py.typed
coveo_systools/streams.py
coveo_systools/subprocess.py
coveo_systools-3.0.1.dist-info/METADATA
coveo_systools-3.0.1.dist-info/WHEEL
coveo_systools-3.0.1.dist-info/RECORD
