Metadata-Version: 2.1
Name: coveo-systools
Version: 3.0.1
Summary: Filesystem, language and OS related tools.
Home-page: https://github.com/coveooss/coveo-python-oss/tree/main/coveo-systools
License: Apache-2.0
Author: Jonathan Piché
Author-email: tools@coveo.com
Requires-Python: >=3.9,<4
Classifier: License :: OSI Approved :: Apache Software License
Classifier: Programming Language :: Python :: 3
Classifier: Programming Language :: Python :: 3.9
Classifier: Programming Language :: Python :: 3.10
Classifier: Programming Language :: Python :: 3.11
Requires-Dist: coveo-functools
Requires-Dist: typing_extensions
Project-URL: Repository, https://github.com/coveooss/coveo-python-oss/tree/main/coveo-systools
